dsbapi/__init__.py
dsbapi/dsb.py
dsbapi/events.py
dsbapi/substitutions.py
dsbapi-3.5.1.dist-info/METADATA
dsbapi-3.5.1.dist-info/WHEEL
dsbapi-3.5.1.dist-info/top_level.txt
dsbapi-3.5.1.dist-info/RECORD
