Metadata-Version: 2.1
Name: dsbapi
Version: 3.5.1
Summary: UNKNOWN
Home-page: UNKNOWN
Author: FJ Tech
Author-email: fjtech.team@gmail.com
License: MIT
Platform: UNKNOWN
Requires-Dist: beautifulsoup4
Requires-Dist: requests
Requires-Dist: mashumaro
Requires-Dist: icalendar
